quivr_sphinx_autodoc/__init__.py
quivr_sphinx_autodoc/__version__.py
quivr_sphinx_autodoc/extension.py
quivr_sphinx_autodoc-0.2.0.dist-info/METADATA
quivr_sphinx_autodoc-0.2.0.dist-info/WHEEL
quivr_sphinx_autodoc-0.2.0.dist-info/licenses/LICENSE.txt
quivr_sphinx_autodoc-0.2.0.dist-info/RECORD
