Metadata-Version: 2.1
Name: quivr-sphinx-autodoc
Version: 0.2.0
Project-URL: Documentation, https://github.com/unknown/quivr-sphinx-autodoc#readme
Project-URL: Issues, https://github.com/unknown/quivr-sphinx-autodoc/issues
Project-URL: Source, https://github.com/unknown/quivr-sphinx-autodoc
Author-email: Spencer Nelson <spencer@b612foundation.org>
License-Expression: MIT
License-File: LICENSE.txt
Classifier: Development Status :: 4 - Beta
Classifier: Programming Language :: Python
Classifier: Programming Language :: Python :: 3.7
Classifier: Programming Language :: Python :: 3.8
Classifier: Programming Language :: Python :: 3.9
Classifier: Programming Language :: Python :: 3.10
Classifier: Programming Language :: Python :: 3.11
Classifier: Programming Language :: Python :: Implementation :: CPython
Classifier: Programming Language :: Python :: Implementation :: PyPy
Requires-Python: >=3.7
Requires-Dist: quivr
Requires-Dist: sphinx
